{"time":{"updated":"Jun 18, 2021 19:08:00 UTC","updatedISO":"2021-06-18T19:08:00+00:00","updateduk":"Jun 18, 2021 at 20:08 BST"},"disclaimer":"This data was produced from the CoinDesk Bitcoin Price Index (USD). Non-USD currency data converted using hourly conversion rate from openexchangerates.org","chartName":"Bitcoin","bpi":{"USD":{"code":"USD","symbol":"&#36;","rate":"35,462.0317","description":"United States Dollar","rate_float":35462.0317},"GBP":{"code":"GBP","symbol":"&pound;","rate":"25,661.7801","description":"British Pound Sterling","rate_float":25661.7801},"EUR":{"code":"EUR","symbol":"&euro;","rate":"29,871.4424","description":"Euro","rate_float":29871.4424},"CNY":{"code":"CNY","symbol":"&yen;","rate":"40,202.5000","description":"Chinese Yuan","rate_float":40202.5}}}