{"time":{"updated":"Jun 29, 2021 23:18:00 UTC","updatedISO":"2021-06-29T23:18:00+00:00","updateduk":"Jun 30, 2021 at 00:18 BST"},"disclaimer":"This data was produced from the CoinDesk Bitcoin Price Index (USD). Non-USD currency data converted using hourly conversion rate from openexchangerates.org","chartName":"Bitcoin","bpi":{"USD":{"code":"USD","symbol":"&#36;","rate":"35,900.0250","description":"United States Dollar","rate_float":35900.025},"GBP":{"code":"GBP","symbol":"&pound;","rate":"25,932.9216","description":"British Pound Sterling","rate_float":25932.9216},"EUR":{"code":"EUR","symbol":"&euro;","rate":"30,169.1963","description":"Euro","rate_float":30169.1963},"CNY":{"code":"CNY","symbol":"&yen;","rate":"40,202.5000","description":"Chinese Yuan","rate_float":40202.5}}}