{"time":{"updated":"Aug 5, 2021 07:25:00 UTC","updatedISO":"2021-08-05T07:25:00+00:00","updateduk":"Aug 5, 2021 at 08:25 BST"},"disclaimer":"This data was produced from the CoinDesk Bitcoin Price Index (USD). Non-USD currency data converted using hourly conversion rate from openexchangerates.org","chartName":"Bitcoin","bpi":{"USD":{"code":"USD","symbol":"&#36;","rate":"38,896.7400","description":"United States Dollar","rate_float":38896.74},"GBP":{"code":"GBP","symbol":"&pound;","rate":"27,985.7766","description":"British Pound Sterling","rate_float":27985.7766},"EUR":{"code":"EUR","symbol":"&euro;","rate":"32,858.3323","description":"Euro","rate_float":32858.3323},"CNY":{"code":"CNY","symbol":"&yen;","rate":"40,202.5000","description":"Chinese Yuan","rate_float":40202.5}}}